pdtf.py
pdtf-1.0.5.dist-info/licenses/LICENSE
pdtf-1.0.5.dist-info/WHEEL
pdtf-1.0.5.dist-info/METADATA
pdtf-1.0.5.dist-info/RECORD
