Metadata-Version: 2.4
Name: pdtf
Version: 1.0.5
Summary: Module
Author: Den*Ram
License-Expression: MIT
License-File: LICENSE
